setuptools_cpp_cuda/__init__.py
setuptools_cpp_cuda/build_ext.py
setuptools_cpp_cuda/extension.py
setuptools_cpp_cuda/find_cuda.py
setuptools_cpp_cuda/ninja_build.py
setuptools_cpp_cuda/nvml.py
setuptools_cpp_cuda/utils.py
setuptools_cpp_cuda-0.1.7.dist-info/entry_points.txt
setuptools_cpp_cuda-0.1.7.dist-info/LICENSE
setuptools_cpp_cuda-0.1.7.dist-info/WHEEL
setuptools_cpp_cuda-0.1.7.dist-info/METADATA
setuptools_cpp_cuda-0.1.7.dist-info/RECORD
